deck_of_cards/__init__.py
deck_of_cards/_nbdev.py
deck_of_cards/card.py
deck_of_cards/core.py
deck_of_cards/deck.py
deck_of_cardsT-0.0.2.dist-info/LICENSE
deck_of_cardsT-0.0.2.dist-info/METADATA
deck_of_cardsT-0.0.2.dist-info/WHEEL
deck_of_cardsT-0.0.2.dist-info/entry_points.txt
deck_of_cardsT-0.0.2.dist-info/top_level.txt
deck_of_cardsT-0.0.2.dist-info/RECORD
