Metadata-Version: 2.1
Name: deck-of-cardsT
Version: 0.0.2
Summary: "A minimal example of nbdev using code from Allen Downey's Think Python 2nd Ed"
Home-page: https://github.com/SanderML/deck_of_cardsT/tree/master/
Author: Luca Sander
Author-email: luca.sander@online.de
License: Apache Software License 2.0
Keywords: nbdev
Platform: UNKNOWN
Classifier: Development Status :: 3 - Alpha
Classifier: Intended Audience :: Developers
Classifier: Natural Language :: English
Classifier: Programming Language :: Python :: 3.6
Classifier: Programming Language :: Python :: 3.7
Classifier: Programming Language :: Python :: 3.8
Classifier: License :: OSI Approved :: Apache Software License
Requires-Python: >=3.6
License-File: LICENSE
Requires-Dist: pip
Requires-Dist: packaging
Provides-Extra: dev
